README.md
setup.py
rc_client.egg-info/PKG-INFO
rc_client.egg-info/SOURCES.txt
rc_client.egg-info/dependency_links.txt
rc_client.egg-info/requires.txt
rc_client.egg-info/top_level.txt
rc_python/__init__.py
rc_python/rest_client.py
rc_python/subscription.py