Metadata-Version: 2.1
Name: rc-client
Version: 0.0.1
Summary: Ringcentral API wrapper for Python
Home-page: https://github.com/aarozhkov/rc_client.git
Author: Aleksandr Rozhkov
Author-email: alexander.rozhkov@nordigy.ru
License: GPL
Platform: UNKNOWN
Classifier: Programming Language :: Python :: 3
Classifier: Operating System :: OS Independent
Requires-Python: >=3.6
